socks.py
sockshandler.py
libsock-1.1.0.dist-info/LICENSE
libsock-1.1.0.dist-info/METADATA
libsock-1.1.0.dist-info/WHEEL
libsock-1.1.0.dist-info/top_level.txt
libsock-1.1.0.dist-info/RECORD
