Metadata-Version: 2.1
Name: libsock
Version: 1.1.0
Summary: A Python SOCKS client module. See https://github.com/Anorov/libsock for more information.
Home-page: https://github.com/Anorov/libsock
Author: Anorov
Author-email: anorov.vorona@gmail.com
License: BSD
Keywords: socks,proxy
Classifier: Programming Language :: Python :: 2
Classifier: Programming Language :: Python :: 2.7
Classifier: Programming Language :: Python :: 3
Classifier: Programming Language :: Python :: 3.4
Classifier: Programming Language :: Python :: 3.5
Classifier: Programming Language :: Python :: 3.6
Requires-Python: >=2.7, !=3.0.*, !=3.1.*, !=3.2.*, !=3.3.*
License-File: LICENSE
